{
    "artist_name": "Giovanni Motta",
    "meme_name": "Vital Energy",
    "description": "\"Vital Energy\" is a piece of art that captivates the imagination with its visual narrative and its emotive message. The protagonist of this story is a child named Jonny Boy, a curious and adventurous soul who transcends the limitations of reality.   \n   \nThe artwork opens with Jonny Boy gracefully soaring amidst the clouds, arms spread wide like wings, his gaze filled with wonder and fear at the same time. This image symbolizes childhood, a time of discovery and uncertainty where every moment is a new adventure.   \n   \nHowever, the scene takes an unexpected turn when Jonny Boy is struck by a cascade of arrows materializing out of nowhere.  This detail emphasizes that even when Jonny Boy faces challenges and obstacles, he must maintain faith in himself and his journey. JonnyBoy represents each of us struggling and enduring to improve this difficult world.    \n   \nI dedicated this work to WAGMI because this phrase is magical, it unites people in a feeling of belonging and mutual support. When you say or share this acronym, you create a bond with others who share the same spirit of determination and confidence in the future.   \n  \nMeme: 2  \nSeason: 3  \nCard: 3",
    "token_id": "115",
    "image_url": "https://arweave.net/B0cghKBhYJ7ZaBc2WxKjPW4hXQGDdLS-iSsZgKs72lM",
    "thumbnail": "https://res.cloudinary.com/alchemyapi/image/upload/thumbnailv2/eth-mainnet/5d9270ea5b6df0b6d9bd0e81c04d73f0"
}